cjio/__init__.py
cjio/cityjson.py
cjio/cjio.py
cjio/convert.py
cjio/errors.py
cjio/floatEncoder.py
cjio/geom_help.py
cjio/subset.py
cjio/utils.py
cjio-0.10.1.dist-info/licenses/LICENSE
cjio-0.10.1.dist-info/METADATA
cjio-0.10.1.dist-info/WHEEL
cjio-0.10.1.dist-info/entry_points.txt
cjio-0.10.1.dist-info/top_level.txt
cjio-0.10.1.dist-info/RECORD
