Metadata-Version: 2.4
Name: cjio
Version: 0.10.1
Summary: CLI to process and manipulate CityJSON files
Home-page: https://github.com/cityjson/cjio
Author: Hugo Ledoux, Balázs Dukai, Gina Stavropoulou
Author-email: h.ledoux@tudelft.nl, balazs.dukai@3dgi.nl, g.stavropoulou@tudelft.nl
License: MIT
Classifier: Development Status :: 3 - Alpha
Classifier: Intended Audience :: Science/Research
Classifier: Topic :: Scientific/Engineering :: GIS
Classifier: License :: OSI Approved :: MIT License
Classifier: Programming Language :: Python :: 3
Classifier: Operating System :: POSIX :: Linux
Classifier: Operating System :: MacOS :: MacOS X
Classifier: Operating System :: Microsoft :: Windows
Requires-Python: >=3.6
License-File: LICENSE
Requires-Dist: numpy
Requires-Dist: Click>=8.1.0
Provides-Extra: develop
Requires-Dist: pytest; extra == "develop"
Requires-Dist: bump2version; extra == "develop"
Requires-Dist: coverage; extra == "develop"
Provides-Extra: export
Requires-Dist: pandas; extra == "export"
Requires-Dist: mapbox-earcut; extra == "export"
Requires-Dist: triangle2; extra == "export"
Provides-Extra: validate
Requires-Dist: cjvalpy>=0.3.0; extra == "validate"
Provides-Extra: reproject
Requires-Dist: pyproj>=3.0.0; extra == "reproject"
Dynamic: author
Dynamic: author-email
Dynamic: classifier
Dynamic: description
Dynamic: description-content-type
Dynamic: home-page
Dynamic: license
Dynamic: license-file
Dynamic: provides-extra
Dynamic: requires-dist
Dynamic: requires-python
Dynamic: summary
